herd_python/__init__.py
herd_python/client.py
herd_python/keyvaluestore_pb2.py
herd_python/keyvaluestore_pb2_grpc.py
herd_python/test.py
herd_python-0.1.15.dist-info/METADATA
herd_python-0.1.15.dist-info/WHEEL
herd_python-0.1.15.dist-info/top_level.txt
herd_python-0.1.15.dist-info/RECORD
