Metadata-Version: 2.2
Name: herd-python
Version: 0.1.15
Summary: gRPC client library for Herd service
Author-email: Anthony DeFoe <defoe.am@gmail.com>
Project-URL: Homepage, https://github.com/defoeam/Herd-Python
Requires-Python: >=3.7
Requires-Dist: grpcio>=1.51.1
Requires-Dist: grpcio-tools>=1.51.1
